
{"items":[{"name":"TAssetBundle","href":"TAssetBundle.html","topicHref":"TAssetBundle.html","topicUid":"TAssetBundle","items":[{"name":"AssetBundleDownloadInfo","href":"TAssetBundle.AssetBundleDownloadInfo.html","topicHref":"TAssetBundle.AssetBundleDownloadInfo.html","topicUid":"TAssetBundle.AssetBundleDownloadInfo"},{"name":"AssetBundleDownloadInfo.DownloadInfo","href":"TAssetBundle.AssetBundleDownloadInfo.DownloadInfo.html","topicHref":"TAssetBundle.AssetBundleDownloadInfo.DownloadInfo.html","topicUid":"TAssetBundle.AssetBundleDownloadInfo.DownloadInfo"},{"name":"AssetBundleDownloadInfo.EDownloadState","href":"TAssetBundle.AssetBundleDownloadInfo.EDownloadState.html","topicHref":"TAssetBundle.AssetBundleDownloadInfo.EDownloadState.html","topicUid":"TAssetBundle.AssetBundleDownloadInfo.EDownloadState"},{"name":"AssetBundleInfo","href":"TAssetBundle.AssetBundleInfo.html","topicHref":"TAssetBundle.AssetBundleInfo.html","topicUid":"TAssetBundle.AssetBundleInfo"},{"name":"AssetBundleRuntimeInfo","href":"TAssetBundle.AssetBundleRuntimeInfo.html","topicHref":"TAssetBundle.AssetBundleRuntimeInfo.html","topicUid":"TAssetBundle.AssetBundleRuntimeInfo"},{"name":"AssetCatalog","href":"TAssetBundle.AssetCatalog.html","topicHref":"TAssetBundle.AssetCatalog.html","topicUid":"TAssetBundle.AssetCatalog"},{"name":"AssetHandle","href":"TAssetBundle.AssetHandle.html","topicHref":"TAssetBundle.AssetHandle.html","topicUid":"TAssetBundle.AssetHandle"},{"name":"AssetHandle<T>","href":"TAssetBundle.AssetHandle-1.html","topicHref":"TAssetBundle.AssetHandle-1.html","topicUid":"TAssetBundle.AssetHandle`1","name.vb":"AssetHandle(Of T)"},{"name":"AssetRef","href":"TAssetBundle.AssetRef.html","topicHref":"TAssetBundle.AssetRef.html","topicUid":"TAssetBundle.AssetRef"},{"name":"AssetTypeAttribute","href":"TAssetBundle.AssetTypeAttribute.html","topicHref":"TAssetBundle.AssetTypeAttribute.html","topicUid":"TAssetBundle.AssetTypeAttribute"},{"name":"AsyncOperationExtensions","href":"TAssetBundle.AsyncOperationExtensions.html","topicHref":"TAssetBundle.AsyncOperationExtensions.html","topicUid":"TAssetBundle.AsyncOperationExtensions"},{"name":"AsyncOperationPool","href":"TAssetBundle.AsyncOperationPool.html","topicHref":"TAssetBundle.AsyncOperationPool.html","topicUid":"TAssetBundle.AsyncOperationPool"},{"name":"AudioClipAssetRef","href":"TAssetBundle.AudioClipAssetRef.html","topicHref":"TAssetBundle.AudioClipAssetRef.html","topicUid":"TAssetBundle.AudioClipAssetRef"},{"name":"CatalogFileHandler","href":"TAssetBundle.CatalogFileHandler.html","topicHref":"TAssetBundle.CatalogFileHandler.html","topicUid":"TAssetBundle.CatalogFileHandler"},{"name":"CatalogSerializer","href":"TAssetBundle.CatalogSerializer.html","topicHref":"TAssetBundle.CatalogSerializer.html","topicUid":"TAssetBundle.CatalogSerializer"},{"name":"CoreObject","href":"TAssetBundle.CoreObject.html","topicHref":"TAssetBundle.CoreObject.html","topicUid":"TAssetBundle.CoreObject"},{"name":"CryptoSerializer","href":"TAssetBundle.CryptoSerializer.html","topicHref":"TAssetBundle.CryptoSerializer.html","topicUid":"TAssetBundle.CryptoSerializer"},{"name":"DataStructureExtensions","href":"TAssetBundle.DataStructureExtensions.html","topicHref":"TAssetBundle.DataStructureExtensions.html","topicUid":"TAssetBundle.DataStructureExtensions"},{"name":"DefaultAssetCatalogComparer","href":"TAssetBundle.DefaultAssetCatalogComparer.html","topicHref":"TAssetBundle.DefaultAssetCatalogComparer.html","topicUid":"TAssetBundle.DefaultAssetCatalogComparer"},{"name":"DefaultTagComparer","href":"TAssetBundle.DefaultTagComparer.html","topicHref":"TAssetBundle.DefaultTagComparer.html","topicUid":"TAssetBundle.DefaultTagComparer"},{"name":"Defines","href":"TAssetBundle.Defines.html","topicHref":"TAssetBundle.Defines.html","topicUid":"TAssetBundle.Defines"},{"name":"EBuildIncludeAssetBundle","href":"TAssetBundle.EBuildIncludeAssetBundle.html","topicHref":"TAssetBundle.EBuildIncludeAssetBundle.html","topicUid":"TAssetBundle.EBuildIncludeAssetBundle"},{"name":"EEditorPlayMode","href":"TAssetBundle.EEditorPlayMode.html","topicHref":"TAssetBundle.EEditorPlayMode.html","topicUid":"TAssetBundle.EEditorPlayMode"},{"name":"FolderAssetRef","href":"TAssetBundle.FolderAssetRef.html","topicHref":"TAssetBundle.FolderAssetRef.html","topicUid":"TAssetBundle.FolderAssetRef"},{"name":"FolderAssetTypeAttribute","href":"TAssetBundle.FolderAssetTypeAttribute.html","topicHref":"TAssetBundle.FolderAssetTypeAttribute.html","topicUid":"TAssetBundle.FolderAssetTypeAttribute"},{"name":"GameObjectAssetRef","href":"TAssetBundle.GameObjectAssetRef.html","topicHref":"TAssetBundle.GameObjectAssetRef.html","topicUid":"TAssetBundle.GameObjectAssetRef"},{"name":"IActiveAssetBundleInfo","href":"TAssetBundle.IActiveAssetBundleInfo.html","topicHref":"TAssetBundle.IActiveAssetBundleInfo.html","topicUid":"TAssetBundle.IActiveAssetBundleInfo"},{"name":"IAssetCatalogComparer","href":"TAssetBundle.IAssetCatalogComparer.html","topicHref":"TAssetBundle.IAssetCatalogComparer.html","topicUid":"TAssetBundle.IAssetCatalogComparer"},{"name":"IAssetCatalogInfo","href":"TAssetBundle.IAssetCatalogInfo.html","topicHref":"TAssetBundle.IAssetCatalogInfo.html","topicUid":"TAssetBundle.IAssetCatalogInfo"},{"name":"IAssetInfo","href":"TAssetBundle.IAssetInfo.html","topicHref":"TAssetBundle.IAssetInfo.html","topicUid":"TAssetBundle.IAssetInfo"},{"name":"IAsyncOperation","href":"TAssetBundle.IAsyncOperation.html","topicHref":"TAssetBundle.IAsyncOperation.html","topicUid":"TAssetBundle.IAsyncOperation"},{"name":"IAsyncOperationPool","href":"TAssetBundle.IAsyncOperationPool.html","topicHref":"TAssetBundle.IAsyncOperationPool.html","topicUid":"TAssetBundle.IAsyncOperationPool"},{"name":"IReferenceCount","href":"TAssetBundle.IReferenceCount.html","topicHref":"TAssetBundle.IReferenceCount.html","topicUid":"TAssetBundle.IReferenceCount"},{"name":"ITagComparer","href":"TAssetBundle.ITagComparer.html","topicHref":"TAssetBundle.ITagComparer.html","topicUid":"TAssetBundle.ITagComparer"},{"name":"JsonCatalogSerializer","href":"TAssetBundle.JsonCatalogSerializer.html","topicHref":"TAssetBundle.JsonCatalogSerializer.html","topicUid":"TAssetBundle.JsonCatalogSerializer"},{"name":"LoadSceneInfo","href":"TAssetBundle.LoadSceneInfo.html","topicHref":"TAssetBundle.LoadSceneInfo.html","topicUid":"TAssetBundle.LoadSceneInfo"},{"name":"LoadSceneInfo.AllowSceneActivationCallback","href":"TAssetBundle.LoadSceneInfo.AllowSceneActivationCallback.html","topicHref":"TAssetBundle.LoadSceneInfo.AllowSceneActivationCallback.html","topicUid":"TAssetBundle.LoadSceneInfo.AllowSceneActivationCallback"},{"name":"Logger","href":"TAssetBundle.Logger.html","topicHref":"TAssetBundle.Logger.html","topicUid":"TAssetBundle.Logger"},{"name":"RijndaelCryptoSerializer","href":"TAssetBundle.RijndaelCryptoSerializer.html","topicHref":"TAssetBundle.RijndaelCryptoSerializer.html","topicUid":"TAssetBundle.RijndaelCryptoSerializer"},{"name":"SceneAssetRef","href":"TAssetBundle.SceneAssetRef.html","topicHref":"TAssetBundle.SceneAssetRef.html","topicUid":"TAssetBundle.SceneAssetRef"},{"name":"Settings","href":"TAssetBundle.Settings.html","topicHref":"TAssetBundle.Settings.html","topicUid":"TAssetBundle.Settings"},{"name":"Settings.BuildSetting","href":"TAssetBundle.Settings.BuildSetting.html","topicHref":"TAssetBundle.Settings.BuildSetting.html","topicUid":"TAssetBundle.Settings.BuildSetting"},{"name":"SpriteAssetRef","href":"TAssetBundle.SpriteAssetRef.html","topicHref":"TAssetBundle.SpriteAssetRef.html","topicUid":"TAssetBundle.SpriteAssetRef"},{"name":"TAssetBundles","href":"TAssetBundle.TAssetBundles.html","topicHref":"TAssetBundle.TAssetBundles.html","topicUid":"TAssetBundle.TAssetBundles"},{"name":"TAsyncOperation","href":"TAssetBundle.TAsyncOperation.html","topicHref":"TAssetBundle.TAsyncOperation.html","topicUid":"TAssetBundle.TAsyncOperation"},{"name":"TAsyncOperationBase","href":"TAssetBundle.TAsyncOperationBase.html","topicHref":"TAssetBundle.TAsyncOperationBase.html","topicUid":"TAssetBundle.TAsyncOperationBase"},{"name":"TAsyncOperationExtensions","href":"TAssetBundle.TAsyncOperationExtensions.html","topicHref":"TAssetBundle.TAsyncOperationExtensions.html","topicUid":"TAssetBundle.TAsyncOperationExtensions"},{"name":"TAsyncOperationProgress<ResultType>","href":"TAssetBundle.TAsyncOperationProgress-1.html","topicHref":"TAssetBundle.TAsyncOperationProgress-1.html","topicUid":"TAssetBundle.TAsyncOperationProgress`1","name.vb":"TAsyncOperationProgress(Of ResultType)"},{"name":"TAsyncOperation<ResultType>","href":"TAssetBundle.TAsyncOperation-1.html","topicHref":"TAssetBundle.TAsyncOperation-1.html","topicUid":"TAssetBundle.TAsyncOperation`1","name.vb":"TAsyncOperation(Of ResultType)"},{"name":"UnityWebRequestError","href":"TAssetBundle.UnityWebRequestError.html","topicHref":"TAssetBundle.UnityWebRequestError.html","topicUid":"TAssetBundle.UnityWebRequestError"},{"name":"UnityWebRequestExtensions","href":"TAssetBundle.UnityWebRequestExtensions.html","topicHref":"TAssetBundle.UnityWebRequestExtensions.html","topicUid":"TAssetBundle.UnityWebRequestExtensions"},{"name":"Util","href":"TAssetBundle.Util.html","topicHref":"TAssetBundle.Util.html","topicUid":"TAssetBundle.Util"},{"name":"WebRequestAsync","href":"TAssetBundle.WebRequestAsync.html","topicHref":"TAssetBundle.WebRequestAsync.html","topicUid":"TAssetBundle.WebRequestAsync"},{"name":"WebRequestCallback","href":"TAssetBundle.WebRequestCallback.html","topicHref":"TAssetBundle.WebRequestCallback.html","topicUid":"TAssetBundle.WebRequestCallback"},{"name":"WebRequestCommand","href":"TAssetBundle.WebRequestCommand.html","topicHref":"TAssetBundle.WebRequestCommand.html","topicUid":"TAssetBundle.WebRequestCommand"},{"name":"WebRequestCommandAssetBundle","href":"TAssetBundle.WebRequestCommandAssetBundle.html","topicHref":"TAssetBundle.WebRequestCommandAssetBundle.html","topicUid":"TAssetBundle.WebRequestCommandAssetBundle"},{"name":"WebRequestCommandGet","href":"TAssetBundle.WebRequestCommandGet.html","topicHref":"TAssetBundle.WebRequestCommandGet.html","topicUid":"TAssetBundle.WebRequestCommandGet"}]},{"name":"TAssetBundle.Editor","href":"TAssetBundle.Editor.html","topicHref":"TAssetBundle.Editor.html","topicUid":"TAssetBundle.Editor","items":[{"name":"AssetBundleBuildInfo","href":"TAssetBundle.Editor.AssetBundleBuildInfo.html","topicHref":"TAssetBundle.Editor.AssetBundleBuildInfo.html","topicUid":"TAssetBundle.Editor.AssetBundleBuildInfo"},{"name":"AssetBundleBuilder","href":"TAssetBundle.Editor.AssetBundleBuilder.html","topicHref":"TAssetBundle.Editor.AssetBundleBuilder.html","topicUid":"TAssetBundle.Editor.AssetBundleBuilder"},{"name":"AssetListWindow","href":"TAssetBundle.Editor.AssetListWindow.html","topicHref":"TAssetBundle.Editor.AssetListWindow.html","topicUid":"TAssetBundle.Editor.AssetListWindow"},{"name":"ClearCompositionStrategy","href":"TAssetBundle.Editor.ClearCompositionStrategy.html","topicHref":"TAssetBundle.Editor.ClearCompositionStrategy.html","topicUid":"TAssetBundle.Editor.ClearCompositionStrategy"},{"name":"CompositionStrategyBuildData","href":"TAssetBundle.Editor.CompositionStrategyBuildData.html","topicHref":"TAssetBundle.Editor.CompositionStrategyBuildData.html","topicUid":"TAssetBundle.Editor.CompositionStrategyBuildData"},{"name":"CompositionStrategyInfo","href":"TAssetBundle.Editor.CompositionStrategyInfo.html","topicHref":"TAssetBundle.Editor.CompositionStrategyInfo.html","topicUid":"TAssetBundle.Editor.CompositionStrategyInfo"},{"name":"CompositionStrategyInfoPropertyDrawer","href":"TAssetBundle.Editor.CompositionStrategyInfoPropertyDrawer.html","topicHref":"TAssetBundle.Editor.CompositionStrategyInfoPropertyDrawer.html","topicUid":"TAssetBundle.Editor.CompositionStrategyInfoPropertyDrawer"},{"name":"DefaultCompositionStrategy","href":"TAssetBundle.Editor.DefaultCompositionStrategy.html","topicHref":"TAssetBundle.Editor.DefaultCompositionStrategy.html","topicUid":"TAssetBundle.Editor.DefaultCompositionStrategy"},{"name":"DefaultCompositionStrategy.ECompositionType","href":"TAssetBundle.Editor.DefaultCompositionStrategy.ECompositionType.html","topicHref":"TAssetBundle.Editor.DefaultCompositionStrategy.ECompositionType.html","topicUid":"TAssetBundle.Editor.DefaultCompositionStrategy.ECompositionType"},{"name":"EAssetBundleBuildName","href":"TAssetBundle.Editor.EAssetBundleBuildName.html","topicHref":"TAssetBundle.Editor.EAssetBundleBuildName.html","topicUid":"TAssetBundle.Editor.EAssetBundleBuildName"},{"name":"EditorGUIUtil","href":"TAssetBundle.Editor.EditorGUIUtil.html","topicHref":"TAssetBundle.Editor.EditorGUIUtil.html","topicUid":"TAssetBundle.Editor.EditorGUIUtil"},{"name":"EditorUtil","href":"TAssetBundle.Editor.EditorUtil.html","topicHref":"TAssetBundle.Editor.EditorUtil.html","topicUid":"TAssetBundle.Editor.EditorUtil"},{"name":"ExcludeObjectsCompositionStrategyData","href":"TAssetBundle.Editor.ExcludeObjectsCompositionStrategyData.html","topicHref":"TAssetBundle.Editor.ExcludeObjectsCompositionStrategyData.html","topicUid":"TAssetBundle.Editor.ExcludeObjectsCompositionStrategyData"},{"name":"ExcludeObjectsStrategy","href":"TAssetBundle.Editor.ExcludeObjectsStrategy.html","topicHref":"TAssetBundle.Editor.ExcludeObjectsStrategy.html","topicUid":"TAssetBundle.Editor.ExcludeObjectsStrategy"},{"name":"FixedCompositionStrategy","href":"TAssetBundle.Editor.FixedCompositionStrategy.html","topicHref":"TAssetBundle.Editor.FixedCompositionStrategy.html","topicUid":"TAssetBundle.Editor.FixedCompositionStrategy"},{"name":"FixedCompositionStrategyData","href":"TAssetBundle.Editor.FixedCompositionStrategyData.html","topicHref":"TAssetBundle.Editor.FixedCompositionStrategyData.html","topicUid":"TAssetBundle.Editor.FixedCompositionStrategyData"},{"name":"RegexMatchCompositionStrategy","href":"TAssetBundle.Editor.RegexMatchCompositionStrategy.html","topicHref":"TAssetBundle.Editor.RegexMatchCompositionStrategy.html","topicUid":"TAssetBundle.Editor.RegexMatchCompositionStrategy"},{"name":"RegexMatchCompositionStrategyData","href":"TAssetBundle.Editor.RegexMatchCompositionStrategyData.html","topicHref":"TAssetBundle.Editor.RegexMatchCompositionStrategyData.html","topicUid":"TAssetBundle.Editor.RegexMatchCompositionStrategyData"},{"name":"RegexMatchDeleteCompositionStrategy","href":"TAssetBundle.Editor.RegexMatchDeleteCompositionStrategy.html","topicHref":"TAssetBundle.Editor.RegexMatchDeleteCompositionStrategy.html","topicUid":"TAssetBundle.Editor.RegexMatchDeleteCompositionStrategy"},{"name":"ReorderableListHelper","href":"TAssetBundle.Editor.ReorderableListHelper.html","topicHref":"TAssetBundle.Editor.ReorderableListHelper.html","topicUid":"TAssetBundle.Editor.ReorderableListHelper"},{"name":"SameNameCompositionStrategy","href":"TAssetBundle.Editor.SameNameCompositionStrategy.html","topicHref":"TAssetBundle.Editor.SameNameCompositionStrategy.html","topicUid":"TAssetBundle.Editor.SameNameCompositionStrategy"},{"name":"TAssetBundleCompositionStrategy","href":"TAssetBundle.Editor.TAssetBundleCompositionStrategy.html","topicHref":"TAssetBundle.Editor.TAssetBundleCompositionStrategy.html","topicUid":"TAssetBundle.Editor.TAssetBundleCompositionStrategy"},{"name":"TAssetBundleCompositionStrategy.Data","href":"TAssetBundle.Editor.TAssetBundleCompositionStrategy.Data.html","topicHref":"TAssetBundle.Editor.TAssetBundleCompositionStrategy.Data.html","topicUid":"TAssetBundle.Editor.TAssetBundleCompositionStrategy.Data"},{"name":"TAssetBundleCompositionStrategy<T>","href":"TAssetBundle.Editor.TAssetBundleCompositionStrategy-1.html","topicHref":"TAssetBundle.Editor.TAssetBundleCompositionStrategy-1.html","topicUid":"TAssetBundle.Editor.TAssetBundleCompositionStrategy`1","name.vb":"TAssetBundleCompositionStrategy(Of T)"},{"name":"TAssetBundleManifest","href":"TAssetBundle.Editor.TAssetBundleManifest.html","topicHref":"TAssetBundle.Editor.TAssetBundleManifest.html","topicUid":"TAssetBundle.Editor.TAssetBundleManifest"},{"name":"TAssetBundleManifestCache","href":"TAssetBundle.Editor.TAssetBundleManifestCache.html","topicHref":"TAssetBundle.Editor.TAssetBundleManifestCache.html","topicUid":"TAssetBundle.Editor.TAssetBundleManifestCache"},{"name":"TAssetBundleManifestUtil","href":"TAssetBundle.Editor.TAssetBundleManifestUtil.html","topicHref":"TAssetBundle.Editor.TAssetBundleManifestUtil.html","topicUid":"TAssetBundle.Editor.TAssetBundleManifestUtil"},{"name":"TagInfo","href":"TAssetBundle.Editor.TagInfo.html","topicHref":"TAssetBundle.Editor.TagInfo.html","topicUid":"TAssetBundle.Editor.TagInfo"},{"name":"TextFieldEditorWindow","href":"TAssetBundle.Editor.TextFieldEditorWindow.html","topicHref":"TAssetBundle.Editor.TextFieldEditorWindow.html","topicUid":"TAssetBundle.Editor.TextFieldEditorWindow"}]},{"name":"TAssetBundle.Extensions","href":"TAssetBundle.Extensions.html","topicHref":"TAssetBundle.Extensions.html","topicUid":"TAssetBundle.Extensions","items":[{"name":"AssetInfo","href":"TAssetBundle.Extensions.AssetInfo.html","topicHref":"TAssetBundle.Extensions.AssetInfo.html","topicUid":"TAssetBundle.Extensions.AssetInfo"},{"name":"AssetInfo.EFlag","href":"TAssetBundle.Extensions.AssetInfo.EFlag.html","topicHref":"TAssetBundle.Extensions.AssetInfo.EFlag.html","topicUid":"TAssetBundle.Extensions.AssetInfo.EFlag"},{"name":"AssetInfo<T>","href":"TAssetBundle.Extensions.AssetInfo-1.html","topicHref":"TAssetBundle.Extensions.AssetInfo-1.html","topicUid":"TAssetBundle.Extensions.AssetInfo`1","name.vb":"AssetInfo(Of T)"},{"name":"AssetLinker","href":"TAssetBundle.Extensions.AssetLinker.html","topicHref":"TAssetBundle.Extensions.AssetLinker.html","topicUid":"TAssetBundle.Extensions.AssetLinker"},{"name":"AssetLinkerExtensions","href":"TAssetBundle.Extensions.AssetLinkerExtensions.html","topicHref":"TAssetBundle.Extensions.AssetLinkerExtensions.html","topicUid":"TAssetBundle.Extensions.AssetLinkerExtensions"},{"name":"AssetLinkerInspector","href":"TAssetBundle.Extensions.AssetLinkerInspector.html","topicHref":"TAssetBundle.Extensions.AssetLinkerInspector.html","topicUid":"TAssetBundle.Extensions.AssetLinkerInspector"},{"name":"AssetManager","href":"TAssetBundle.Extensions.AssetManager.html","topicHref":"TAssetBundle.Extensions.AssetManager.html","topicUid":"TAssetBundle.Extensions.AssetManager"},{"name":"AssetManager.LoadPrefabDelegate","href":"TAssetBundle.Extensions.AssetManager.LoadPrefabDelegate.html","topicHref":"TAssetBundle.Extensions.AssetManager.LoadPrefabDelegate.html","topicUid":"TAssetBundle.Extensions.AssetManager.LoadPrefabDelegate"},{"name":"AssetPrefabPool","href":"TAssetBundle.Extensions.AssetPrefabPool.html","topicHref":"TAssetBundle.Extensions.AssetPrefabPool.html","topicUid":"TAssetBundle.Extensions.AssetPrefabPool"},{"name":"AssetPrefabPoolInspector","href":"TAssetBundle.Extensions.AssetPrefabPoolInspector.html","topicHref":"TAssetBundle.Extensions.AssetPrefabPoolInspector.html","topicUid":"TAssetBundle.Extensions.AssetPrefabPoolInspector"},{"name":"AsyncOperation","href":"TAssetBundle.Extensions.AsyncOperation.html","topicHref":"TAssetBundle.Extensions.AsyncOperation.html","topicUid":"TAssetBundle.Extensions.AsyncOperation"},{"name":"AsyncOperationExtensions","href":"TAssetBundle.Extensions.AsyncOperationExtensions.html","topicHref":"TAssetBundle.Extensions.AsyncOperationExtensions.html","topicUid":"TAssetBundle.Extensions.AsyncOperationExtensions"},{"name":"AsyncOperation<T>","href":"TAssetBundle.Extensions.AsyncOperation-1.html","topicHref":"TAssetBundle.Extensions.AsyncOperation-1.html","topicUid":"TAssetBundle.Extensions.AsyncOperation`1","name.vb":"AsyncOperation(Of T)"},{"name":"GetProgressDelegate","href":"TAssetBundle.Extensions.GetProgressDelegate.html","topicHref":"TAssetBundle.Extensions.GetProgressDelegate.html","topicUid":"TAssetBundle.Extensions.GetProgressDelegate"},{"name":"IGetProgressable","href":"TAssetBundle.Extensions.IGetProgressable.html","topicHref":"TAssetBundle.Extensions.IGetProgressable.html","topicUid":"TAssetBundle.Extensions.IGetProgressable"},{"name":"PrefabPool","href":"TAssetBundle.Extensions.PrefabPool.html","topicHref":"TAssetBundle.Extensions.PrefabPool.html","topicUid":"TAssetBundle.Extensions.PrefabPool"},{"name":"PrefabPoolDelegate","href":"TAssetBundle.Extensions.PrefabPoolDelegate.html","topicHref":"TAssetBundle.Extensions.PrefabPoolDelegate.html","topicUid":"TAssetBundle.Extensions.PrefabPoolDelegate"},{"name":"PrefabPoolInspector","href":"TAssetBundle.Extensions.PrefabPoolInspector.html","topicHref":"TAssetBundle.Extensions.PrefabPoolInspector.html","topicUid":"TAssetBundle.Extensions.PrefabPoolInspector"},{"name":"PrefabPoolManager","href":"TAssetBundle.Extensions.PrefabPoolManager.html","topicHref":"TAssetBundle.Extensions.PrefabPoolManager.html","topicUid":"TAssetBundle.Extensions.PrefabPoolManager"},{"name":"PrefabPooledObject","href":"TAssetBundle.Extensions.PrefabPooledObject.html","topicHref":"TAssetBundle.Extensions.PrefabPooledObject.html","topicUid":"TAssetBundle.Extensions.PrefabPooledObject"},{"name":"PrefabPooledObjectExtensions","href":"TAssetBundle.Extensions.PrefabPooledObjectExtensions.html","topicHref":"TAssetBundle.Extensions.PrefabPooledObjectExtensions.html","topicUid":"TAssetBundle.Extensions.PrefabPooledObjectExtensions"}]}],"memberLayout":"SamePage"}